pathway_assessor/__init__.py
pathway_assessor/pathway_assessor.py
pathway_assessor/databases/hallmark.pkl
pathway_assessor/databases/hmdb_smpdb.pkl
pathway_assessor/databases/kegg.pkl
pathway_assessor/databases/reactome.pkl
tests/__init__.py
tests/test_pathway_assessor.py
pathway_assessor-0.0.4.dist-info/LICENSE
pathway_assessor-0.0.4.dist-info/METADATA
pathway_assessor-0.0.4.dist-info/WHEEL
pathway_assessor-0.0.4.dist-info/top_level.txt
pathway_assessor-0.0.4.dist-info/RECORD
