Metadata-Version: 2.1
Name: pathway-assessor
Version: 0.0.4
Summary: For assessing the overrepresentation and underrepresentation of pathway genes in a given expression table
Home-page: https://github.com/annapamma/PathwayAssessor
Author: Anna Calinawan
Author-email: anna.calinawan@mssm.edu
License: MIT
Platform: UNKNOWN
Classifier: Programming Language :: Python :: 3
Classifier: License :: OSI Approved :: MIT License
Classifier: Operating System :: OS Independent
Requires-Dist: numpy
Requires-Dist: scipy
Requires-Dist: pandas
